gisweb_pagopa_schema/__init__.py
gisweb_pagopa_schema/models.py
gisweb_pagopa_schema/schemas.py
gisweb_pagopa_schema/uuid6.py
gisweb_pagopa_schema-0.3.dist-info/METADATA
gisweb_pagopa_schema-0.3.dist-info/WHEEL
gisweb_pagopa_schema-0.3.dist-info/RECORD
